word2ket/EmbeddingKet.py
word2ket/__init__.py
word2ket/utils.py
word2ket-0.0.2.dist-info/LICENSE
word2ket-0.0.2.dist-info/METADATA
word2ket-0.0.2.dist-info/WHEEL
word2ket-0.0.2.dist-info/top_level.txt
word2ket-0.0.2.dist-info/RECORD
