Metadata-Version: 2.1
Name: word2ket
Version: 0.0.2
Summary: word2ket is an effiecient embedding layer for PyTorch that is inspired by Quantum Entanglement.
Home-page: https://github.com/panaali/word2ket
Author: Ali Panahi
Author-email: panaali@gmail.com
License: BSD-3-Clause
Platform: UNKNOWN
Classifier: Development Status :: 4 - Beta
Classifier: License :: OSI Approved :: BSD License
Classifier: Programming Language :: Python
Classifier: Programming Language :: Python :: 3.5
Classifier: Programming Language :: Python :: 3.6
Classifier: Programming Language :: Python :: 3.7
Classifier: Topic :: Software Development :: Libraries
Classifier: Topic :: Software Development :: Libraries :: Python Modules
Classifier: Topic :: Scientific/Engineering
Classifier: Topic :: Scientific/Engineering :: Artificial Intelligence
Requires-Python: >=3.5
Requires-Dist: torch
Requires-Dist: gpytorch
